<annotation>
	<folder>dandelion</folder>
	<filename>10919961_0af657c4e8.jpg</filename>
	<path>H:\Tensorflow\custom_models\image_classifier\flower_photos\dandelion\10919961_0af657c4e8.jpg</path>
	<source>
		<database>Unknown</database>
	</source>
	<size>
		<width>500</width>
		<height>375</height>
		<depth>3</depth>
	</size>
	<segmented>0</segmented>
	<object>
		<name>dandelion</name>
		<pose>Unspecified</pose>
		<truncated>1</truncated>
		<difficult>0</difficult>
		<bndbox>
			<xmin>15</xmin>
			<ymin>2</ymin>
			<xmax>498</xmax>
			<ymax>375</ymax>
		</bndbox>
	</object>
</annotation>
