<annotation>
	<folder>tulips</folder>
	<filename>11746452_5bc1749a36.jpg</filename>
	<path>H:\Tensorflow\custom_models\image_classifier\flower_photos\tulips\11746452_5bc1749a36.jpg</path>
	<source>
		<database>Unknown</database>
	</source>
	<size>
		<width>500</width>
		<height>248</height>
		<depth>3</depth>
	</size>
	<segmented>0</segmented>
	<object>
		<name>tulip</name>
		<pose>Unspecified</pose>
		<truncated>0</truncated>
		<difficult>0</difficult>
		<bndbox>
			<xmin>20</xmin>
			<ymin>152</ymin>
			<xmax>95</xmax>
			<ymax>227</ymax>
		</bndbox>
	</object>
	<object>
		<name>tulip</name>
		<pose>Unspecified</pose>
		<truncated>0</truncated>
		<difficult>0</difficult>
		<bndbox>
			<xmin>3</xmin>
			<ymin>71</ymin>
			<xmax>38</xmax>
			<ymax>106</ymax>
		</bndbox>
	</object>
	<object>
		<name>tulip</name>
		<pose>Unspecified</pose>
		<truncated>1</truncated>
		<difficult>0</difficult>
		<bndbox>
			<xmin>296</xmin>
			<ymin>207</ymin>
			<xmax>337</xmax>
			<ymax>248</ymax>
		</bndbox>
	</object>
	<object>
		<name>tulip</name>
		<pose>Unspecified</pose>
		<truncated>0</truncated>
		<difficult>0</difficult>
		<bndbox>
			<xmin>209</xmin>
			<ymin>103</ymin>
			<xmax>268</xmax>
			<ymax>162</ymax>
		</bndbox>
	</object>
	<object>
		<name>tulip</name>
		<pose>Unspecified</pose>
		<truncated>0</truncated>
		<difficult>0</difficult>
		<bndbox>
			<xmin>175</xmin>
			<ymin>196</ymin>
			<xmax>212</xmax>
			<ymax>233</ymax>
		</bndbox>
	</object>
	<object>
		<name>tulip</name>
		<pose>Unspecified</pose>
		<truncated>0</truncated>
		<difficult>0</difficult>
		<bndbox>
			<xmin>348</xmin>
			<ymin>149</ymin>
			<xmax>416</xmax>
			<ymax>217</ymax>
		</bndbox>
	</object>
	<object>
		<name>tulip</name>
		<pose>Unspecified</pose>
		<truncated>0</truncated>
		<difficult>0</difficult>
		<bndbox>
			<xmin>449</xmin>
			<ymin>95</ymin>
			<xmax>497</xmax>
			<ymax>142</ymax>
		</bndbox>
	</object>
	<object>
		<name>tulip</name>
		<pose>Unspecified</pose>
		<truncated>0</truncated>
		<difficult>0</difficult>
		<bndbox>
			<xmin>338</xmin>
			<ymin>72</ymin>
			<xmax>398</xmax>
			<ymax>132</ymax>
		</bndbox>
	</object>
	<object>
		<name>tulip</name>
		<pose>Unspecified</pose>
		<truncated>0</truncated>
		<difficult>0</difficult>
		<bndbox>
			<xmin>135</xmin>
			<ymin>60</ymin>
			<xmax>189</xmax>
			<ymax>114</ymax>
		</bndbox>
	</object>
	<object>
		<name>tulip</name>
		<pose>Unspecified</pose>
		<truncated>0</truncated>
		<difficult>0</difficult>
		<bndbox>
			<xmin>73</xmin>
			<ymin>75</ymin>
			<xmax>109</xmax>
			<ymax>111</ymax>
		</bndbox>
	</object>
	<object>
		<name>tulip</name>
		<pose>Unspecified</pose>
		<truncated>0</truncated>
		<difficult>0</difficult>
		<bndbox>
			<xmin>22</xmin>
			<ymin>28</ymin>
			<xmax>59</xmax>
			<ymax>65</ymax>
		</bndbox>
	</object>
	<object>
		<name>tulip</name>
		<pose>Unspecified</pose>
		<truncated>0</truncated>
		<difficult>0</difficult>
		<bndbox>
			<xmin>363</xmin>
			<ymin>23</ymin>
			<xmax>394</xmax>
			<ymax>54</ymax>
		</bndbox>
	</object>
	<object>
		<name>tulip</name>
		<pose>Unspecified</pose>
		<truncated>0</truncated>
		<difficult>0</difficult>
		<bndbox>
			<xmin>221</xmin>
			<ymin>14</ymin>
			<xmax>253</xmax>
			<ymax>46</ymax>
		</bndbox>
	</object>
	<object>
		<name>tulip</name>
		<pose>Unspecified</pose>
		<truncated>0</truncated>
		<difficult>0</difficult>
		<bndbox>
			<xmin>86</xmin>
			<ymin>114</ymin>
			<xmax>134</xmax>
			<ymax>162</ymax>
		</bndbox>
	</object>
	<object>
		<name>tulip</name>
		<pose>Unspecified</pose>
		<truncated>0</truncated>
		<difficult>0</difficult>
		<bndbox>
			<xmin>79</xmin>
			<ymin>11</ymin>
			<xmax>106</xmax>
			<ymax>38</ymax>
		</bndbox>
	</object>
	<object>
		<name>tulip</name>
		<pose>Unspecified</pose>
		<truncated>0</truncated>
		<difficult>0</difficult>
		<bndbox>
			<xmin>431</xmin>
			<ymin>30</ymin>
			<xmax>473</xmax>
			<ymax>72</ymax>
		</bndbox>
	</object>
</annotation>
